coml/__init__.py
coml/_version.py
coml/core.py
coml/ipython_utils.py
coml/linter.py
coml/magics.py
coml/prompt_utils.py
coml/configagent/.env.template
coml/configagent/__init__.py
coml/configagent/__main__.py
coml/configagent/cli.py
coml/configagent/constants.py
coml/configagent/experience.py
coml/configagent/knowledge.py
coml/configagent/orm.py
coml/configagent/space.py
coml/configagent/suggest.py
coml/configagent/surrogate_utils.py
coml/configagent/utils.py
coml/js/nbclassic_init.js
coml/prompts/fix_fewshots.json
coml/prompts/fix_fewshots_v2.json
coml/prompts/generate_fewshots.json
coml/prompts/generate_fewshots_kaggle.json
coml/prompts/generate_fewshots_leetcode.json
coml/prompts/generate_fewshots_matplotlib.json
coml/prompts/generate_fewshots_seaborn.json
coml/prompts/generate_fewshots_v2.json
coml/prompts/dataset/coffee_shop/member.csv
coml/prompts/dataset/game_injury/game.csv
coml/prompts/dataset/pilot_record/pilot.csv
coml/prompts/dataset/scientist_1/AssignedTo.csv
coml/prompts/dataset/scientist_1/Projects.csv
coml/vis_utils/__init__.py
coml/vis_utils/deconstruct.py
coml/vis_utils/verifier.py
mlcopilot-0.0.8.data/data/share/jupyter/labextensions/coml/package.json
mlcopilot-0.0.8.data/data/share/jupyter/labextensions/coml/static/568.c5cdb70ce3b4ff7d2cda.js
mlcopilot-0.0.8.data/data/share/jupyter/labextensions/coml/static/remoteEntry.39c2768f35ebfac23462.js
mlcopilot-0.0.8.data/data/share/jupyter/labextensions/coml/static/style.js
mlcopilot-0.0.8.data/data/share/jupyter/labextensions/coml/static/third-party-licenses.json
mlcopilot-0.0.8.data/data/share/jupyter/labextensions/coml/install.json
mlcopilot-0.0.8.dist-info/METADATA
mlcopilot-0.0.8.dist-info/WHEEL
mlcopilot-0.0.8.dist-info/entry_points.txt
mlcopilot-0.0.8.dist-info/licenses/LICENSE
mlcopilot-0.0.8.dist-info/RECORD
