Metadata-Version: 2.3
Name: mlcopilot
Version: 0.0.8
Summary: Assistant for data scientists and machine learning developers.
Project-URL: Documentation, https://github.com/microsoft/coml#readme
Project-URL: Issues, https://github.com/microsoft/coml/issues
Project-URL: Source, https://github.com/microsoft/coml
Author-email: CoML team <coml@microsoft.com>
License:     MIT License
License-File: LICENSE
Classifier: Development Status :: 4 - Beta
Classifier: Framework :: Jupyter
Classifier: Framework :: Jupyter :: JupyterLab
Classifier: Framework :: Jupyter :: JupyterLab :: 4
Classifier: Framework :: Jupyter :: JupyterLab :: Extensions
Classifier: Framework :: Jupyter :: JupyterLab :: Extensions :: Prebuilt
Classifier: Programming Language :: Python
Classifier: Programming Language :: Python :: 3.8
Classifier: Programming Language :: Python :: 3.9
Classifier: Programming Language :: Python :: 3.10
Classifier: Programming Language :: Python :: 3.11
Requires-Python: >=3.8
Requires-Dist: click
Requires-Dist: colorama
Requires-Dist: ipylab
Requires-Dist: ipython
Requires-Dist: ipywidgets
Requires-Dist: langchain
Requires-Dist: langchain-community
Requires-Dist: langchain-openai
Requires-Dist: markdown
Requires-Dist: numpy
Requires-Dist: orjson
Requires-Dist: pandas
Requires-Dist: peewee
Requires-Dist: psycopg2-binary
Requires-Dist: pylint
Requires-Dist: python-dotenv
Requires-Dist: scikit-learn
Requires-Dist: tiktoken
Requires-Dist: typing-extensions
Requires-Dist: typing-inspect
Requires-Dist: xgboost
Provides-Extra: dev
Requires-Dist: black; extra == 'dev'
Requires-Dist: flake8; extra == 'dev'
Requires-Dist: isort; extra == 'dev'
Requires-Dist: pre-commit; extra == 'dev'
Requires-Dist: pytest; extra == 'dev'
